dataclasses_fromdict/__init__.py
dataclasses_fromdict-0.0.1.dist-info/LICENSE
dataclasses_fromdict-0.0.1.dist-info/METADATA
dataclasses_fromdict-0.0.1.dist-info/WHEEL
dataclasses_fromdict-0.0.1.dist-info/top_level.txt
dataclasses_fromdict-0.0.1.dist-info/RECORD
