Metadata-Version: 2.1
Name: dataclasses-fromdict
Version: 0.0.1
Summary: UNKNOWN
Home-page: https://github.com/Cologler/dataclasses_fromdict-python
Author: cologler
Author-email: skyoflw@gmail.com
License: MIT
Keywords: python,dataclass,fromdict
Platform: UNKNOWN
